epstein_files/__init__.py
epstein_files/documents/communication.py
epstein_files/documents/document.py
epstein_files/documents/email.py
epstein_files/documents/emails/email_header.py
epstein_files/documents/imessage/text_message.py
epstein_files/documents/json_file.py
epstein_files/documents/messenger_log.py
epstein_files/documents/other_file.py
epstein_files/epstein_files.py
epstein_files/person.py
epstein_files/util/constant/common_words.py
epstein_files/util/constant/html.py
epstein_files/util/constant/names.py
epstein_files/util/constant/output_files.py
epstein_files/util/constant/strings.py
epstein_files/util/constant/urls.py
epstein_files/util/constants.py
epstein_files/util/data.py
epstein_files/util/doc_cfg.py
epstein_files/util/env.py
epstein_files/util/file_helper.py
epstein_files/util/highlighted_group.py
epstein_files/util/logging.py
epstein_files/util/output.py
epstein_files/util/rich.py
epstein_files/util/search_result.py
epstein_files/util/timer.py
epstein_files/util/word_count.py
epstein_files-1.4.1.dist-info/LICENSE
epstein_files-1.4.1.dist-info/METADATA
epstein_files-1.4.1.dist-info/WHEEL
epstein_files-1.4.1.dist-info/entry_points.txt
epstein_files-1.4.1.dist-info/RECORD
