Metadata-Version: 2.1
Name: epstein-files
Version: 1.4.1
Summary: Tools for working with the Jeffrey Epstein documents released in November 2025.
Home-page: https://michelcrypt4d4mus.github.io/epstein_text_messages/
License: GPL-3.0-or-later
Keywords: Epstein,Jeffrey Epstein
Author: Michel de Cryptadamus
Requires-Python: >=3.11,<4.0
Classifier: Development Status :: 5 - Production/Stable
Classifier: Environment :: Console
Classifier: Intended Audience :: Information Technology
Classifier: License :: OSI Approved :: GNU General Public License v3 or later (GPLv3+)
Classifier: Programming Language :: Python
Classifier: Programming Language :: Python :: 3
Classifier: Programming Language :: Python :: 3.11
Classifier: Programming Language :: Python :: 3.10
Classifier: Programming Language :: Python :: 3.12
Classifier: Programming Language :: Python :: 3.13
Requires-Dist: cairosvg (>=2.8.2,<3.0.0)
Requires-Dist: datefinder (>=0.7.3,<0.8.0)
Requires-Dist: inflection (>=0.5.1,<0.6.0)
Requires-Dist: python-dateutil (>=2.9.0.post0,<3.0.0)
Requires-Dist: python-dotenv (>=1.2.1,<2.0.0)
Requires-Dist: requests (>=2.32.5,<3.0.0)
Requires-Dist: rich (>=14.2.0,<15.0.0)
Requires-Dist: rich-argparse-plus (>=0.3.1.4,<0.4.0.0)
Project-URL: Emails, https://michelcrypt4d4mus.github.io/epstein_text_messages/all_emails_epstein_files_nov_2025.html
Project-URL: Metadata, https://michelcrypt4d4mus.github.io/epstein_text_messages/file_metadata_epstein_files_nov_2025.json
Project-URL: Repository, https://github.com/michelcrypt4d4mus/epstein_text_messages
Project-URL: TextMessages, https://michelcrypt4d4mus.github.io/epstein_text_messages
Project-URL: WordCounts, https://michelcrypt4d4mus.github.io/epstein_text_messages/communication_word_count_epstein_files_nov_2025.html
